aws_cdk/cx_api/__init__.py
aws_cdk/cx_api/py.typed
aws_cdk/cx_api/_jsii/__init__.py
aws_cdk/cx_api/_jsii/cx-api@2.236.0.jsii.tgz
aws_cdk_cx_api-2.236.0.dist-info/LICENSE
aws_cdk_cx_api-2.236.0.dist-info/METADATA
aws_cdk_cx_api-2.236.0.dist-info/NOTICE
aws_cdk_cx_api-2.236.0.dist-info/WHEEL
aws_cdk_cx_api-2.236.0.dist-info/top_level.txt
aws_cdk_cx_api-2.236.0.dist-info/RECORD
